{
  "$schema": "../../assetlist.schema.json",
  "chainName": "sgetestnet4",
  "assets": [
    {
      "description": "The SGE token is primarily a governance token for the SGE Network blockchain.",
      "denomUnits": [
        {
          "denom": "usge",
          "exponent": 0
        },
        {
          "denom": "sge",
          "exponent": 6
        }
      ],
      "base": "usge",
      "name": "SGE Testnet4",
      "display": "sge",
      "symbol": "SGE",
      "traces": [
        {
          "type": "additional-mintage",
          "counterparty": {
            "chainName": "sgetestnet",
            "baseDenom": "usge"
          },
          "provider": "SGE"
        }
      ],
      "assetType": "sdk.coin"
    }
  ]
}