{
  "$schema": "../assetlist.schema.json",
  "chainName": "source",
  "assets": [
    {
      "description": "The native token of SOURCE Chain",
      "denomUnits": [
        {
          "denom": "usource",
          "exponent": 0
        },
        {
          "denom": "source",
          "exponent": 6
        }
      ],
      "base": "usource",
      "name": "Source",
      "display": "source",
      "symbol": "SOURCE",
      "coingeckoId": "source",
      "assetType": "sdk.coin"
    },
    {
      "description": "Source Protocol's SRCX Token Bridged from BNB Through Planq",
      "denomUnits": [
        {
          "denom": "ibc/FC5A7360EEED0713AE3E83E9D55A69AF873056A172AC495890ACE4582FF9685A",
          "exponent": 0,
          "aliases": [
            "nsrcx"
          ]
        },
        {
          "denom": "srcx",
          "exponent": 9
        }
      ],
      "assetType": "ics20",
      "base": "ibc/FC5A7360EEED0713AE3E83E9D55A69AF873056A172AC495890ACE4582FF9685A",
      "name": "SRCX",
      "display": "srcx",
      "symbol": "SRCX",
      "traces": [
        {
          "type": "ibc",
          "counterparty": {
            "chainName": "planq",
            "baseDenom": "erc20/0x091F9A57A3F58d758b6572E9d41675918EAC7F09",
            "channelId": "channel-61"
          },
          "chain": {
            "channelId": "channel-1",
            "path": "transfer/channel-1/erc20/0x091F9A57A3F58d758b6572E9d41675918EAC7F09"
          }
        }
      ]
    }
  ]
}